{
  "sections": {
    "announcement": {
      "type": "announcement-bar",
      "settings": {
        "text": "FREE WORLDWIDE SHIPPING ON ORDERS OVER 100 EUR"
      }
    },
    "hero": {
      "type": "hero-slideshow",
      "settings": {
        "heading": "I SEE, YOU FEEL.",
        "subheading": "WEAR WHAT YOU FEEL",
        "button_label": "EXPLORE",
        "button_url": "/collections/all"
      }
    },
    "featured": {
      "type": "featured-collection",
      "settings": {
        "heading": "THE SELECTION",
        "subheading": "Our curated picks",
        "products_to_show": 4
      }
    },
    "categories": {
      "type": "category-grid",
      "settings": {},
      "blocks": {
        "cat_women": {
          "type": "category",
          "settings": {
            "title": "WOMEN",
            "button_label": "DISCOVER",
            "link": "/collections/women"
          }
        },
        "cat_men": {
          "type": "category",
          "settings": {
            "title": "MEN",
            "button_label": "DISCOVER",
            "link": "/collections/men"
          }
        },
        "cat_accessories": {
          "type": "category",
          "settings": {
            "title": "ACCESSORIES",
            "button_label": "DISCOVER",
            "link": "/collections/accessories"
          }
        },
        "cat_rituels": {
          "type": "category",
          "settings": {
            "title": "RITUELS",
            "button_label": "DISCOVER",
            "link": "/collections/rituels"
          }
        }
      },
      "block_order": [
        "cat_women",
        "cat_men",
        "cat_accessories",
        "cat_rituels"
      ]
    },
    "story": {
      "type": "image-with-text",
      "settings": {
        "heading": "What I see, you feel.",
        "text": "Every piece we create carries an emotion. Every design tells a story. I SEE, YOU FEEL. is more than a brand - it is a way to express what words cannot.",
        "link_text": "Read our story",
        "link_url": "/pages/about"
      }
    },
    "collections": {
      "type": "two-items-grid",
      "settings": {},
      "blocks": {
        "grid_premium": {
          "type": "card",
          "settings": {
            "title": "ISYF PREMIUM",
            "button_label": "SHOP NOW",
            "link": "/collections/all"
          }
        },
        "grid_feels": {
          "type": "card",
          "settings": {
            "title": "ISYF FEELS",
            "button_label": "SHOP NOW",
            "link": "/collections/all"
          }
        }
      },
      "block_order": [
        "grid_premium",
        "grid_feels"
      ]
    },
    "articles": {
      "type": "article-grid",
      "settings": {
        "heading": "FROM THE JOURNAL",
        "articles_to_show": 3
      }
    },
    "testimonials": {
      "type": "testimonials",
      "settings": {
        "heading": "WHAT THEY SAY"
      },
      "blocks": {
        "testimonial_1": {
          "type": "testimonial",
          "settings": {
            "quote": "The embroidered hoodie is the softest thing I have ever worn. The quality is unreal.",
            "author": "Sara J."
          }
        },
        "testimonial_2": {
          "type": "testimonial",
          "settings": {
            "quote": "I love that every piece has a message. ISYF FEELS tees are my go-to.",
            "author": "Alex M."
          }
        },
        "testimonial_3": {
          "type": "testimonial",
          "settings": {
            "quote": "Finally a brand that gets it. Premium quality without the pretentious price tag.",
            "author": "Kim L."
          }
        }
      },
      "block_order": [
        "testimonial_1",
        "testimonial_2",
        "testimonial_3"
      ]
    },
    "instagram": {
      "type": "instagram-feed",
      "settings": {
        "subtitle": "Follow us on Instagram",
        "heading": "@ISYF_OFF",
        "instagram_url": "https://instagram.com/isyf_off"
      },
      "blocks": {
        "ig_1": {
          "type": "image"
        },
        "ig_2": {
          "type": "image"
        },
        "ig_3": {
          "type": "image"
        },
        "ig_4": {
          "type": "image"
        },
        "ig_5": {
          "type": "image"
        }
      },
      "block_order": [
        "ig_1",
        "ig_2",
        "ig_3",
        "ig_4",
        "ig_5"
      ]
    },
    "subscribe": {
      "type": "subscribe",
      "settings": {
        "heading": "JOIN THE FEELING",
        "description": "Subscribe to receive exclusive drops, early access, and stories from the ISYF universe."
      }
    },
    "footer": {
      "type": "footer",
      "settings": {}
    }
  },
  "order": [
    "announcement",
    "hero",
    "featured",
    "categories",
    "story",
    "collections",
    "articles",
    "testimonials",
    "instagram",
    "subscribe",
    "footer"
  ]
}
